[
  {
    "data": {
      "假名": "ずつう",
      "汉字": "頭痛",
      "中文": "头痛",
      "例句": "頭痛がひどい。",
      "词性": "名词",
      "日语干扰词": [
        "腹痛",
        "発熱",
        "吐き気",
        "めまい",
        "風邪",
        "咳"
      ],
      "中文干扰词": [
        "腹痛",
        "发热",
        "恶心",
        "眩晕",
        "感冒",
        "咳嗽"
      ]
    }
  },
  {
    "data": {
      "假名": "なおる",
      "汉字": "治る",
      "中文": "痊愈",
      "例句": "風邪が治った。",
      "词性": "自动词",
      "日语干扰词": [
        "治す",
        "直る",
        "回復",
        "完治",
        "悪化",
        "発病"
      ],
      "中文干扰词": [
        "治好",
        "修好",
        "恢复",
        "痊愈",
        "恶化",
        "发病"
      ]
    }
  },
  {
    "data": {
      "假名": "かんじゃ",
      "汉字": "患者",
      "中文": "患者",
      "例句": "患者を診る。",
      "词性": "名词",
      "日语干扰词": [
        "医者",
        "看護師",
        "病人",
        "入院",
        "外来",
        "見舞い"
      ],
      "中文干扰词": [
        "医生",
        "护士",
        "病人",
        "住院",
        "门诊",
        "探病"
      ]
    }
  },
  {
    "data": {
      "假名": "ねつ",
      "汉字": "熱",
      "中文": "发烧",
      "例句": "熱がある。",
      "词性": "名词",
      "日语干扰词": [
        "風邪",
        "熱中症",
        "高温",
        "体温",
        "火",
        "温度"
      ],
      "中文干扰词": [
        "感冒",
        "中暑",
        "高温",
        "体温",
        "火",
        "温度"
      ]
    }
  },
  {
    "data": {
      "假名": "げーむ",
      "汉字": "ゲーム",
      "中文": "游戏",
      "例句": "ゲームで遊ぶ。",
      "词性": "名词",
      "日语干扰词": [
        "スポーツ",
        "遊び",
        "勉強",
        "仕事",
        "趣味",
        "試合"
      ],
      "中文干扰词": [
        "运动",
        "玩耍",
        "学习",
        "工作",
        "爱好",
        "比赛"
      ]
    }
  },
  {
    "data": {
      "假名": "きず",
      "汉字": "傷",
      "中文": "伤口",
      "例句": "傷が痛む。",
      "词性": "名词",
      "日语干扰词": [
        "怪我",
        "病気",
        "傷跡",
        "切り傷",
        "擦り傷",
        "打撲"
      ],
      "中文干扰词": [
        "受伤",
        "疾病",
        "伤疤",
        "刀伤",
        "擦伤",
        "挫伤"
      ]
    }
  },
  {
    "data": {
      "假名": "いたむ",
      "汉字": "痛む",
      "中文": "疼痛",
      "例句": "歯が痛む。",
      "词性": "自动词",
      "日语干扰词": [
        "痛い",
        "痒い",
        "苦しい",
        "辛い",
        "傷む",
        "腫れる"
      ],
      "中文干扰词": [
        "疼",
        "痒",
        "痛苦",
        "辛苦",
        "变质",
        "肿胀"
      ]
    }
  },
  {
    "data": {
      "假名": "ひどい",
      "汉字": "",
      "中文": "严重的",
      "例句": "ひどい風邪を引いた。",
      "词性": "形容词",
      "日语干扰词": [
        "大変",
        "すごい",
        "悪い",
        "重い",
        "辛い",
        "厳しい"
      ],
      "中文干扰词": [
        "糟糕",
        "厉害",
        "不好",
        "沉重",
        "辛苦",
        "严格"
      ]
    }
  },
  {
    "data": {
      "假名": "きく",
      "汉字": "効く",
      "中文": "见效",
      "例句": "この薬はよく効く。",
      "词性": "自动词",
      "日语干扰词": [
        "聞く",
        "効き目",
        "作用",
        "働く",
        "動く",
        "治る"
      ],
      "中文干扰词": [
        "听",
        "效果",
        "作用",
        "工作",
        "移动",
        "痊愈"
      ]
    }
  },
  {
    "data": {
      "假名": "かんごし",
      "汉字": "看護師",
      "中文": "护士",
      "例句": "看護師が患者を助ける。",
      "词性": "名词",
      "日语干扰词": [
        "医者",
        "介護士",
        "助産師",
        "薬剤師",
        "看護",
        "先生"
      ],
      "中文干扰词": [
        "医生",
        "护工",
        "助产士",
        "药剂师",
        "护理",
        "老师"
      ]
    }
  },
  {
    "data": {
      "假名": "のう",
      "汉字": "脳",
      "中文": "大脑",
      "例句": "脳の病気を治療する。",
      "词性": "名词",
      "日语干扰词": [
        "心臓",
        "頭",
        "神経",
        "体",
        "背骨",
        "肺"
      ],
      "中文干扰词": [
        "心脏",
        "头",
        "神经",
        "身体",
        "脊柱",
        "肺"
      ]
    }
  },
  {
    "data": {
      "假名": "ひじ",
      "汉字": "肘",
      "中文": "手肘",
      "例句": "肘をぶつけた。",
      "词性": "名词",
      "日语干扰词": [
        "膝",
        "肩",
        "手首",
        "指",
        "足首",
        "腰"
      ],
      "中文干扰词": [
        "膝盖",
        "肩膀",
        "手腕",
        "手指",
        "脚踝",
        "腰"
      ]
    }
  },
  {
    "data": {
      "假名": "みまい",
      "汉字": "見舞い",
      "中文": "探病",
      "例句": "友達を見舞いに行く。",
      "词性": "名词",
      "日语干扰词": [
        "お見舞い",
        "訪問",
        "見物",
        "招待",
        "看病",
        "外来"
      ],
      "中文干扰词": [
        "慰问",
        "访问",
        "观光",
        "招待",
        "看护",
        "门诊"
      ]
    }
  },
  {
    "data": {
      "假名": "はたらく",
      "汉字": "働く",
      "中文": "工作/运作",
      "例句": "心臓が働く。",
      "词性": "动词",
      "日语干扰词": [
        "仕事",
        "動く",
        "働き",
        "動作",
        "機能",
        "効く"
      ],
      "中文干扰词": [
        "工作",
        "移动",
        "作用",
        "动作",
        "机能",
        "见效"
      ]
    }
  },
  {
    "data": {
      "假名": "しんぞう",
      "汉字": "心臓",
      "中文": "心脏",
      "例句": "心臓の手術を受ける。",
      "词性": "名词",
      "日语干扰词": [
        "脳",
        "肺",
        "肝臓",
        "腎臓",
        "胃",
        "腸"
      ],
      "中文干扰词": [
        "大脑",
        "肺",
        "肝脏",
        "肾脏",
        "胃",
        "肠"
      ]
    }
  },
  {
    "data": {
      "假名": "たいいん",
      "汉字": "退院",
      "中文": "出院",
      "例句": "明日退院する予定だ。",
      "词性": "名词",
      "日语干扰词": [
        "入院",
        "外来",
        "通院",
        "退社",
        "退学",
        "退職"
      ],
      "中文干扰词": [
        "住院",
        "门诊",
        "就诊",
        "离职",
        "退学",
        "退休"
      ]
    }
  },
  {
    "data": {
      "假名": "にゅういん",
      "汉字": "入院",
      "中文": "住院",
      "例句": "手術のために入院する。",
      "词性": "名词",
      "日语干扰词": [
        "退院",
        "入学",
        "入社",
        "通院",
        "入国",
        "入場"
      ],
      "中文干扰词": [
        "出院",
        "入学",
        "入职",
        "就诊",
        "入境",
        "入场"
      ]
    }
  },
  {
    "data": {
      "假名": "くしゃみ",
      "汉字": "くしゃみ",
      "中文": "喷嚏",
      "例句": "くしゃみが止まらない。",
      "词性": "名词",
      "日语干扰词": [
        "咳",
        "鼻水",
        "鼻づまり",
        "涙",
        "あくび",
        "げっぷ"
      ],
      "中文干扰词": [
        "咳嗽",
        "鼻涕",
        "鼻塞",
        "眼泪",
        "哈欠",
        "打嗝"
      ]
    }
  },
  {
    "data": {
      "假名": "みがく",
      "汉字": "磨く",
      "中文": "刷（牙）",
      "例句": "歯を磨く。",
      "词性": "他动词",
      "日语干扰词": [
        "磨く",
        "洗う",
        "拭く",
        "磨耗",
        "削る",
        "磨き上げる"
      ],
      "中文干扰词": [
        "打磨",
        "清洗",
        "擦拭",
        "磨损",
        "削",
        "抛光"
      ]
    }
  },
  {
    "data": {
      "假名": "はいしゃ",
      "汉字": "歯医者",
      "中文": "牙医",
      "例句": "歯医者に行く。",
      "词性": "名词",
      "日语干扰词": [
        "医者",
        "看護師",
        "薬剤師",
        "歯科",
        "歯",
        "衛生士"
      ],
      "中文干扰词": [
        "医生",
        "护士",
        "药剂师",
        "牙科",
        "牙齿",
        "卫生员"
      ]
    }
  },
  {
    "data": {
      "假名": "せき",
      "汉字": "咳",
      "中文": "咳嗽",
      "例句": "咳が出る。",
      "词性": "名词",
      "日语干扰词": [
        "くしゃみ",
        "鼻水",
        "鼻づまり",
        "痰",
        "喘息",
        "風邪"
      ],
      "中文干扰词": [
        "喷嚏",
        "鼻涕",
        "鼻塞",
        "痰",
        "哮喘",
        "感冒"
      ]
    }
  }
]