[
  {
    "data": {
      "假名": "こくさい",
      "汉字": "国際",
      "中文": "国际",
      "例句": "国際会議に参加する。",
      "词性": "名词",
      "日语干扰词": [
        "国内",
        "国家",
        "世界",
        "海外",
        "外国",
        "全国"
      ],
      "中文干扰词": [
        "国内",
        "国家",
        "世界",
        "海外",
        "外国",
        "全国"
      ]
    }
  },
  {
    "data": {
      "假名": "せいふ",
      "汉字": "政府",
      "中文": "政府",
      "例句": "政府の方針を決める。",
      "词性": "名词",
      "日语干扰词": [
        "政治",
        "国家",
        "議会",
        "政党",
        "行政",
        "官庁"
      ],
      "中文干扰词": [
        "政治",
        "国家",
        "议会",
        "政党",
        "行政",
        "官厅"
      ]
    }
  },
  {
    "data": {
      "假名": "たいし",
      "汉字": "大使",
      "中文": "大使",
      "例句": "日本の大使が訪問する。",
      "词性": "名词",
      "日语干扰词": [
        "大使館",
        "外交官",
        "領事",
        "特使",
        "公使",
        "代表"
      ],
      "中文干扰词": [
        "大使馆",
        "外交官",
        "领事",
        "特使",
        "公使",
        "代表"
      ]
    }
  },
  {
    "data": {
      "假名": "とうりょう",
      "汉字": "統領",
      "中文": "总统",
      "例句": "アメリカの統領が来日する。",
      "词性": "名词",
      "日语干扰词": [
        "大統領",
        "首相",
        "大臣",
        "議員",
        "総理",
        "長官"
      ],
      "中文干扰词": [
        "大总统",
        "首相",
        "大臣",
        "议员",
        "总理",
        "长官"
      ]
    }
  },
  {
    "data": {
      "假名": "だいとうりょう",
      "汉字": "大統領",
      "中文": "总统",
      "例句": "アメリカの大統領が演説する。",
      "词性": "名词",
      "日语干扰词": [
        "統領",
        "首相",
        "総理",
        "大臣",
        "議員",
        "知事"
      ],
      "中文干扰词": [
        "统领",
        "首相",
        "总理",
        "大臣",
        "议员",
        "知事"
      ]
    }
  },
  {
    "data": {
      "假名": "ぎいん",
      "汉字": "議員",
      "中文": "议员",
      "例句": "国会議員が法案を審議する。",
      "词性": "名词",
      "日语干扰词": [
        "議会",
        "政治家",
        "代議士",
        "参議員",
        "衆議院",
        "政党"
      ],
      "中文干扰词": [
        "议会",
        "政治家",
        "代议士",
        "参议员",
        "众议院",
        "政党"
      ]
    }
  },
  {
    "data": {
      "假名": "せいじ",
      "汉字": "政治",
      "中文": "政治",
      "例句": "政治に興味がある。",
      "词性": "名词",
      "日语干扰词": [
        "政府",
        "政策",
        "政党",
        "選挙",
        "議会",
        "行政"
      ],
      "中文干扰词": [
        "政府",
        "政策",
        "政党",
        "选举",
        "议会",
        "行政"
      ]
    }
  },
  {
    "data": {
      "假名": "たいしかん",
      "汉字": "大使館",
      "中文": "大使馆",
      "例句": "大使館でビザを申請する。",
      "词性": "名词",
      "日语干扰词": [
        "大使",
        "領事館",
        "外務省",
        "政府",
        "公館",
        "外交"
      ],
      "中文干扰词": [
        "大使",
        "领事馆",
        "外务省",
        "政府",
        "公馆",
        "外交"
      ]
    }
  },
  {
    "data": {
      "假名": "ひはん",
      "汉字": "批判",
      "中文": "批评",
      "例句": "政策を批判する。",
      "词性": "名词・他动词",
      "日语干扰词": [
        "批評",
        "非難",
        "反対",
        "抗議",
        "異議",
        "反発"
      ],
      "中文干扰词": [
        "批评",
        "非难",
        "反对",
        "抗议",
        "异议",
        "反发"
      ]
    }
  },
  {
    "data": {
      "假名": "こくみん",
      "汉字": "国民",
      "中文": "国民",
      "例句": "国民の意見を聞く。",
      "词性": "名词",
      "日语干扰词": [
        "市民",
        "住民",
        "人民",
        "民族",
        "国家",
        "国籍"
      ],
      "中文干扰词": [
        "市民",
        "居民",
        "人民",
        "民族",
        "国家",
        "国籍"
      ]
    }
  },
  {
    "data": {
      "假名": "ほうあん",
      "汉字": "法案",
      "中文": "法案",
      "例句": "新しい法案が提出された。",
      "词性": "名词",
      "日语干扰词": [
        "法律",
        "条例",
        "規則",
        "制度",
        "提案",
        "議案"
      ],
      "中文干扰词": [
        "法律",
        "条例",
        "规则",
        "制度",
        "提案",
        "议案"
      ]
    }
  },
  {
    "data": {
      "假名": "ぎかい",
      "汉字": "議会",
      "中文": "议会",
      "例句": "議会で法案を審議する。",
      "词性": "名词",
      "日语干扰词": [
        "議員",
        "国会",
        "政府",
        "会議",
        "政治",
        "選挙"
      ],
      "中文干扰词": [
        "议员",
        "国会",
        "政府",
        "会议",
        "政治",
        "选举"
      ]
    }
  },
  {
    "data": {
      "假名": "せいとう",
      "汉字": "政党",
      "中文": "政党",
      "例句": "新しい政党が結成された。",
      "词性": "名词",
      "日语干扰词": [
        "政治",
        "政府",
        "政策",
        "政治家",
        "選挙",
        "党"
      ],
      "中文干扰词": [
        "政治",
        "政府",
        "政策",
        "政治家",
        "选举",
        "党"
      ]
    }
  },
  {
    "data": {
      "假名": "せいど",
      "汉字": "制度",
      "中文": "制度",
      "例句": "新しい制度を導入する。",
      "词性": "名词",
      "日语干扰词": [
        "規則",
        "法律",
        "仕組み",
        "体制",
        "システム",
        "方式"
      ],
      "中文干扰词": [
        "规则",
        "法律",
        "机制",
        "体制",
        "系统",
        "方式"
      ]
    }
  },
  {
    "data": {
      "假名": "かけつ",
      "汉字": "可決",
      "中文": "通过（议案）",
      "例句": "法案が可決された。",
      "词性": "名词・他动词",
      "日语干扰词": [
        "否決",
        "承認",
        "採決",
        "決定",
        "決議",
        "議決"
      ],
      "中文干扰词": [
        "否决",
        "承认",
        "表决",
        "决定",
        "决议",
        "议决"
      ]
    }
  },
  {
    "data": {
      "假名": "ていあん",
      "汉字": "提案",
      "中文": "提案",
      "例句": "新しい提案を出す。",
      "词性": "名词・他动词",
      "日语干扰词": [
        "案",
        "企画",
        "計画",
        "提言",
        "提示",
        "提出"
      ],
      "中文干扰词": [
        "方案",
        "企划",
        "计划",
        "提言",
        "提示",
        "提出"
      ]
    }
  },
  {
    "data": {
      "假名": "もくてき",
      "汉字": "目的",
      "中文": "目的",
      "例句": "旅行の目的を聞く。",
      "词性": "名词",
      "日语干扰词": [
        "目標",
        "狙い",
        "意図",
        "意味",
        "理由",
        "趣旨"
      ],
      "中文干扰词": [
        "目标",
        "目标",
        "意图",
        "意义",
        "理由",
        "宗旨"
      ]
    }
  },
  {
    "data": {
      "假名": "きょうじゅ",
      "汉字": "教授",
      "中文": "教授",
      "例句": "大学の教授に質問する。",
      "词性": "名词",
      "日语干扰词": [
        "先生",
        "教師",
        "講師",
        "助教授",
        "学者",
        "博士"
      ],
      "中文干扰词": [
        "老师",
        "教师",
        "讲师",
        "副教授",
        "学者",
        "博士"
      ]
    }
  },
  {
    "data": {
      "假名": "はたらき",
      "汉字": "働き",
      "中文": "功能/作用",
      "例句": "この薬の働きを調べる。",
      "词性": "名词",
      "日语干扰词": [
        "機能",
        "作用",
        "効果",
        "役割",
        "仕事",
        "動き"
      ],
      "中文干扰词": [
        "机能",
        "作用",
        "效果",
        "作用",
        "工作",
        "动作"
      ]
    }
  }
]